Ios8KaifaRumenFix1/README.md
Ios8KaifaRumenFix1/__init__.py
Ios8KaifaRumenFix1/__main__.py
Ios8KaifaRumenFix1/file.epub
Ios8KaifaRumenFix1/index.html
Ios8KaifaRumenFix1/css/__init__.py
Ios8KaifaRumenFix1/css/annotations.css
Ios8KaifaRumenFix1/css/main.css
Ios8KaifaRumenFix1/css/normalize.css
Ios8KaifaRumenFix1/css/popup.css
Ios8KaifaRumenFix1/font/__init__.py
Ios8KaifaRumenFix1/font/fontello.eot
Ios8KaifaRumenFix1/font/fontello.svg
Ios8KaifaRumenFix1/font/fontello.ttf
Ios8KaifaRumenFix1/font/fontello.woff
Ios8KaifaRumenFix1/img/__init__.py
Ios8KaifaRumenFix1/img/annotator-glyph-sprite.png
Ios8KaifaRumenFix1/img/annotator-icon-sprite.png
Ios8KaifaRumenFix1/img/apple-touch-icon.png
Ios8KaifaRumenFix1/img/cancelfullscreen.png
Ios8KaifaRumenFix1/img/close.png
Ios8KaifaRumenFix1/img/fullscreen.png
Ios8KaifaRumenFix1/img/loader.gif
Ios8KaifaRumenFix1/img/menu-icon.png
Ios8KaifaRumenFix1/img/save.png
Ios8KaifaRumenFix1/img/saved.png
Ios8KaifaRumenFix1/img/settings-s.png
Ios8KaifaRumenFix1/img/settings.png
Ios8KaifaRumenFix1/img/star.png
Ios8KaifaRumenFix1/js/__init__.py
Ios8KaifaRumenFix1/js/epub.js
Ios8KaifaRumenFix1/js/epub.min.js
Ios8KaifaRumenFix1/js/epub.min.map
Ios8KaifaRumenFix1/js/hooks.min.js
Ios8KaifaRumenFix1/js/hooks.min.map
Ios8KaifaRumenFix1/js/reader.js
Ios8KaifaRumenFix1/js/reader.js.map
Ios8KaifaRumenFix1/js/reader.min.js
Ios8KaifaRumenFix1/js/reader.min.map
Ios8KaifaRumenFix1/js/hooks/__init__.py
Ios8KaifaRumenFix1/js/hooks/extensions/__init__.py
Ios8KaifaRumenFix1/js/hooks/extensions/highlight.js
Ios8KaifaRumenFix1/js/libs/__init__.py
Ios8KaifaRumenFix1/js/libs/jquery.min.js
Ios8KaifaRumenFix1/js/libs/localforage.min.js
Ios8KaifaRumenFix1/js/libs/screenfull.js
Ios8KaifaRumenFix1/js/libs/screenfull.min.js
Ios8KaifaRumenFix1/js/libs/zip.min.js
Ios8KaifaRumenFix1/js/plugins/__init__.py
Ios8KaifaRumenFix1/js/plugins/hypothesis.js
Ios8KaifaRumenFix1/js/plugins/search.js
ios8_kaifa_rumen_fix1-2024.3.1.0.dist-info/METADATA
ios8_kaifa_rumen_fix1-2024.3.1.0.dist-info/WHEEL
ios8_kaifa_rumen_fix1-2024.3.1.0.dist-info/entry_points.txt
ios8_kaifa_rumen_fix1-2024.3.1.0.dist-info/top_level.txt
ios8_kaifa_rumen_fix1-2024.3.1.0.dist-info/RECORD
